{
  "title": "Направляющий снаряд",
  "title_en": "Guiding bolt",
  "slug": "178-guiding_bolt",
  "level": 1,
  "item_suffix": "ВС.",
  "schoolSlug": "evocation",
  "classes": [
    13
  ],
  "classesTce": [],
  "archtype": [
    144,
    169,
    190
  ],
  "source": "«Player's handbook»",
  "needsConcentration": false,
  "isRitual": false,
  "castTimeType": "action",
  "castTime": "1 действие",
  "distance": "120 футов",
  "duration": "1 раунд",
  "archtypes": "клятва славы (паладин), круг звёзд (друид), небожитель (колдун)",
  "description": "<p>Вспышка света устремляется к выбранному вами существу в пределах дистанции. Совершите по цели дальнобойную атаку заклинанием. При попадании цель получает 4к6 урона излучением,<span style=\"font-size: 15px;\">&nbsp;и следующий бросок атаки по цели, совершённый до конца вашего следующего хода, совершается с преимуществом благодаря мистическому тусклому свету, недолго остающемуся на цели.</span></p>\n<p><strong><em>На больших уровнях.</em></strong> Если вы накладываете это заклинание, используя ячейку 2-го уровня или выше, урон увеличивается на 1к6 за каждый уровень ячейки выше 1-го.</p>"
}