{
  "title": "Ужасное увядание Аби-Далзима",
  "title_en": "Abi-Dalzim's horrid wilting",
  "slug": "412-abi_dalzim_s_horrid_wilting",
  "level": 8,
  "item_suffix": "ВСМ",
  "schoolSlug": "necromancy",
  "classes": [
    21,
    19
  ],
  "classesTce": [],
  "archtype": [],
  "source": "«Princes of the Apocalypse», «Xanathar's Guide to Everything»",
  "needsConcentration": false,
  "isRitual": false,
  "castTimeType": "action",
  "castTime": "1 действие",
  "distance": "150 футов",
  "duration": "Мгновенная",
  "description": "<p>Вы вытягиваете влагу из всех существ в кубе с длиной ребра 30 футов с центром на указанной вами точке в пределах дистанции. Каждое существо в этой области должно совершить спасбросок Телосложения. Это заклинание не действует на Конструктов и Нежить, а Растения и <a href=\"/bestiary/144-water_elemental/\" target=\"_blank\">водяные элементали [water elemental]</a>&nbsp;совершают спасбросок с помехой. При провале существо получает 12к8 урона некротической энергией или половину этого урона при успехе.</p><p>Немагические растения в области действия заклинания, не являющиеся существами, такие как деревья и кусты, увядают и умирают мгновенно. </p>"
}